corextopic/__init__.py
corextopic/corextopic.py
corextopic/vis_topic.py
corextopic-1.1.dist-info/LICENSE.txt
corextopic-1.1.dist-info/METADATA
corextopic-1.1.dist-info/WHEEL
corextopic-1.1.dist-info/top_level.txt
corextopic-1.1.dist-info/RECORD
