Metadata-Version: 2.1
Name: corextopic
Version: 1.1
Summary: Hierarchical and semi-supervised topic modeling with minimal domain knowledge through Anchored Correlation Explanation
Home-page: https://github.com/gregversteeg/corex_topic
Author: Greg Ver Steeg/Ryan J. Gallagher
Author-email: gregv@isi.edu
License: UNKNOWN
Keywords: topic model,corex,anchored corex,LDA,semi-supervised,hierarchical topic model,information theory
Platform: UNKNOWN
Classifier: Programming Language :: Python
Classifier: Programming Language :: Python :: 3
Classifier: License :: OSI Approved :: Apache Software License
Classifier: Operating System :: OS Independent
